deepclimate/__init__.py
deepclimate/tensorflow/__init__.py
deepclimate/tensorflow/data/__init__.py
deepclimate/tensorflow/losses/__init__.py
deepclimate/tensorflow/losses/losses.py
deepclimate/tensorflow/models/__init__.py
deepclimate/tensorflow/models/resnets.py
deepclimate/tensorflow/models/sequential.py
deepclimate/tensorflow/models/unets.py
deepclimate/tensorflow/train/__init__.py
deepclimate/tensorflow/train/pix2pix.py
deepclimate/tensorflow/train/srgan.py
deepclimate/tensorflow/train/supervised.py
deepclimate/tensorflow/utils/__init__.py
deepclimate/tensorflow/utils/dataload.py
deepclimate/tensorflow/utils/ncutils.py
deepclimate/tensorflow/utils/nputils.py
deepclimate/tensorflow/utils/pltutils.py
deepclimate/tensorflow/utils/tfutils.py
deepclimate/tensorflow/utils/utils_v1.py
deepclimate-0.1.3.dist-info/METADATA
deepclimate-0.1.3.dist-info/WHEEL
deepclimate-0.1.3.dist-info/top_level.txt
deepclimate-0.1.3.dist-info/RECORD
