Metadata-Version: 2.1
Name: deepclimate
Version: 0.1.3
Summary: A deep learning framework for climate modelling and data analysis
Home-page: https://github.com/midhunmachari/DeepClimate
Author: Midhun Murukesh
Author-email: midhunmachari@gmail.com
Classifier: Development Status :: 3 - Alpha
Classifier: Intended Audience :: Science/Research
Classifier: Topic :: Scientific/Engineering
Classifier: License :: OSI Approved :: MIT License
Classifier: Programming Language :: Python :: 3
Classifier: Programming Language :: Python :: 3.9
Classifier: Programming Language :: Python :: 3.10
Classifier: Programming Language :: Python :: 3.11
Classifier: Programming Language :: Python :: 3.12
Classifier: Operating System :: OS Independent
Requires-Python: >=3.9
Requires-Dist: numpy
Requires-Dist: pandas
Requires-Dist: scipy
Requires-Dist: netcdf4
Requires-Dist: tensorflow==2.17.0
Requires-Dist: xarray>=2024.11.0
